testdata/clitable_templateA
testdata/clitable_templateB
testdata/clitable_templateC
testdata/clitable_templateD
testdata/default_index
testdata/nondefault_index
testdata/parseindex_index
testdata/parseindexfail1_index
testdata/parseindexfail2_index
testdata/parseindexfail3_index
textfsm/__init__.py
textfsm/clitable.py
textfsm/copyable_regex_object.py
textfsm/parser.py
textfsm/terminal.py
textfsm/texttable.py
textfsm-1.1.3.dist-info/COPYING
textfsm-1.1.3.dist-info/LICENSE.txt
textfsm-1.1.3.dist-info/METADATA
textfsm-1.1.3.dist-info/WHEEL
textfsm-1.1.3.dist-info/entry_points.txt
textfsm-1.1.3.dist-info/top_level.txt
textfsm-1.1.3.dist-info/RECORD
