Metadata-Version: 2.1
Name: textfsm
Version: 1.1.3
Summary: Python module for parsing semi-structured text into python tables.
Home-page: https://github.com/google/textfsm
Maintainer: Google
Maintainer-email: textfsm-dev@googlegroups.com
License: Apache License, Version 2.0
Platform: UNKNOWN
Classifier: Development Status :: 5 - Production/Stable
Classifier: Intended Audience :: Developers
Classifier: License :: OSI Approved :: Apache Software License
Classifier: Operating System :: OS Independent
Classifier: Programming Language :: Python :: 2
Classifier: Programming Language :: Python :: 3
Classifier: Topic :: Software Development :: Libraries
